dChol.cpython-312-darwin.so
eigen_solvers.cpython-312-darwin.so
davies.cpython-312-darwin.so
mssm-1.1.2.dist-info/RECORD
mssm-1.1.2.dist-info/WHEEL
mssm-1.1.2.dist-info/top_level.txt
mssm-1.1.2.dist-info/METADATA
mssm-1.1.2.dist-info/licenses/LICENSE
mssm/models.py
mssm/__init__.py
mssm/src/__init__.py
mssm/src/python/terms.py
mssm/src/python/penalties.py
mssm/src/python/file_loading.py
mssm/src/python/formula.py
mssm/src/python/compact_rep.py
mssm/src/python/__init__.py
mssm/src/python/exp_fam.py
mssm/src/python/gamm_solvers.py
mssm/src/python/repara.py
mssm/src/python/matrix_solvers.py
mssm/src/python/utils.py
mssm/src/python/custom_types.py
mssm/src/python/smooths.py
mssm/src/python/compare.py
mssm/src/cpp/dchol.cpp
mssm/src/cpp/eigen_solvers.cpp
mssm/src/cpp/davies.cpp
