Metadata-Version: 2.4
Name: mssm
Version: 1.1.2
Summary: Toolbox for estimating Generalized Additive Mixed Models (GAMMs), Generalized Additive Mixed Models of Location Scale and Shape (GAMMLSS), and more general smooth models.
Author-email: Joshua Krause <jokra001@proton.me>
Classifier: Programming Language :: Python :: 3
Classifier: Operating System :: OS Independent
Requires-Python: >=3.10
License-File: LICENSE
Requires-Dist: numpy>=1.24.1
Requires-Dist: pandas>=1.5.3
Requires-Dist: scipy>=1.15.0
Requires-Dist: tqdm>=4.66.1
Provides-Extra: mp
Requires-Dist: multiprocess>=0.70.18; extra == "mp"
Provides-Extra: plot
Requires-Dist: mssmViz==0.1.49; extra == "plot"
Provides-Extra: dev
Requires-Dist: mssm[plot]; extra == "dev"
Requires-Dist: pytest>=8.3.5; extra == "dev"
Requires-Dist: pytest-cov>=6.1.1; extra == "dev"
Requires-Dist: numdifftools>=0.9.41; extra == "dev"
Requires-Dist: flake8; extra == "dev"
Requires-Dist: sphinx>=8.1.3; extra == "dev"
Requires-Dist: sphinx-rtd-theme>=3.0.2; extra == "dev"
Requires-Dist: myst-nb>=1.3.0; extra == "dev"
Dynamic: license-file
